deploy/__init__.py
deploy/__main__.py
deploy/deploy.py
deploy/docker.py
deploy/git.py
deploy/k8s.py
deploy/schema.py
deploy/services.py
deploy/utils.py
python_deploy-4.1.0.data/scripts/kubernetes_use_token
python_deploy-4.1.0.dist-info/LICENSE
python_deploy-4.1.0.dist-info/METADATA
python_deploy-4.1.0.dist-info/WHEEL
python_deploy-4.1.0.dist-info/entry_points.txt
python_deploy-4.1.0.dist-info/top_level.txt
python_deploy-4.1.0.dist-info/RECORD
