Metadata-Version: 2.1
Name: python-deploy
Version: 4.1.0
Summary: Build, push and deploy k8s services with single deploy.json file to provide common convention for multiple production services.
Home-page: https://github.com/CERT-Polska/python-deploy
Author: msm, psrok1
Author-email: info@cert.pl
License: UNKNOWN
Platform: UNKNOWN
Classifier: Programming Language :: Python :: 3
Classifier: Operating System :: OS Independent
Classifier: License :: OSI Approved :: MIT License
Requires-Python: >=3.8
License-File: LICENSE
Requires-Dist: PyYAML (<7.0.0,>=6.0.1)
